deprecation.py
deprecation-2.0.7.dist-info/LICENSE
deprecation-2.0.7.dist-info/METADATA
deprecation-2.0.7.dist-info/WHEEL
deprecation-2.0.7.dist-info/top_level.txt
deprecation-2.0.7.dist-info/RECORD
