Metadata-Version: 1.2
Name: deprecation
Version: 2.0.7
Summary: A library to handle automated deprecations
Home-page: http://deprecation.readthedocs.io/
Author: Brian Curtin
Author-email: brian@python.org
Maintainer: Brian Curtin
Maintainer-email: brian@python.org
License: Apache 2
Project-URL: Documentation, http://deprecation.readthedocs.io/en/latest/
Project-URL: Source, https://github.com/briancurtin/deprecation
Project-URL: Bug Tracker, https://github.com/briancurtin/deprecation/issues
Keywords: deprecation
Platform: UNKNOWN
Classifier: Development Status :: 5 - Production/Stable
Classifier: License :: OSI Approved :: Apache Software License
Classifier: Programming Language :: Python
Classifier: Programming Language :: Python :: 2
Classifier: Programming Language :: Python :: 2.7
Classifier: Programming Language :: Python :: 3
Classifier: Programming Language :: Python :: 3.5
Classifier: Programming Language :: Python :: 3.6
Classifier: Programming Language :: Python :: 3.7
Classifier: Programming Language :: Python :: Implementation :: CPython
Classifier: Programming Language :: Python :: Implementation :: PyPy
Classifier: Topic :: Software Development :: Libraries :: Python Modules
